charmonium/time_block/__init__.py
charmonium/time_block/_cli.py
charmonium/time_block/py.typed
charmonium/time_block/time_block.py
charmonium/time_block/utils.py
charmonium_time_block-0.4.0.dist-info/LICENSE.txt
charmonium_time_block-0.4.0.dist-info/METADATA
charmonium_time_block-0.4.0.dist-info/WHEEL
charmonium_time_block-0.4.0.dist-info/entry_points.txt
charmonium_time_block-0.4.0.dist-info/RECORD
