Metadata-Version: 2.3
Name: charmonium.time_block
Version: 0.4.0
Summary: Time a block of code.
License: MIT
Author: Samuel Grayson
Author-email: sam+dev@samgrayson.me
Requires-Python: >=3.9,<4.0
Classifier: License :: OSI Approved :: MIT License
Classifier: Programming Language :: Python :: 3
Classifier: Programming Language :: Python :: 3.9
Classifier: Programming Language :: Python :: 3.10
Classifier: Programming Language :: Python :: 3.11
Classifier: Programming Language :: Python :: 3.12
Classifier: Programming Language :: Python :: 3.13
Project-URL: Repository, https://github.com/charmoniumQ/charmonium.time_block.git
